{"date": "1973-01-27", "entries": [{"spotifyLink": "https://embed.spotify.com/?uri=spotify:track:4dwrL3Z5U2RZ6MZiKE2PgL", "peakPos": 1, "artist": "Stevie Wonder", "lastPos": 2, "title": "Superstition", "rank": 1, "weeks": 16, "change": "+1"}, {"spotifyLink": "https://embed.spotify.com/?uri=spotify:track:2DnJjbjNTV9Nd5NOa1KGba", "peakPos": 1, "artist": "Carly Simon", "lastPos": 1, "title": "You're So Vain", "rank": 2, "weeks": 17, "change": "-1"}, {"spotifyLink": "https://embed.spotify.com/?uri=spotify:track:5cmIWIBxZj9HpqrVtj4KWG", "peakPos": 1, "artist": "Elton John", "lastPos": 4, "title": "Crocodile Rock", "rank": 3, "weeks": 17, "change": "+1"}, {"spotifyLink": "none", "peakPos": 4, "artist": "Kenny Loggins & Jim Messina", "lastPos": 5, "title": "Your Mama Don't Dance", "rank": 4, "weeks": 16, "change": "+1"}, {"spotifyLink": "https://embed.spotify.com/?uri=spotify:track:722E6CPY8biq4sUnf40u6Y", "peakPos": 3, "artist": "Timmy Thomas", "lastPos": 9, "title": "Why Can't We Live Together", "rank": 5, "weeks": 15, "change": "+4"}, {"spotifyLink": "https://embed.spotify.com/?uri=spotify:track:5GYcaVfaFBHe2gzA6Oybgj", "peakPos": 1, "artist": "Billy Paul", "lastPos": 3, "title": "Me And Mrs. Jones", "rank": 6, "weeks": 16, "change": "-3"}, {"spotifyLink": "https://embed.spotify.com/?uri=spotify:track:7BYkUrzjt02SVH6ohFwBLJ", "peakPos": 3, "artist": "Hurricane Smith", "lastPos": 10, "title": "Oh, Babe, What Would You Say?", "rank": 7, "weeks": 15, "change": "+3"}, {"spotifyLink": "https://embed.spotify.com/?uri=spotify:track:3sPDf67E0fkFHsB8zLT1Ab", "peakPos": 7, "artist": "Marvin Gaye", "lastPos": 13, "title": "Trouble Man", "rank": 8, "weeks": 12, "change": "+5"}, {"spotifyLink": "https://embed.spotify.com/?uri=spotify:track:7sQWTooMlPEmpcYhE2OirG", "peakPos": 6, "artist": "Johnny Rivers", "lastPos": 6, "title": "Rockin' Pneumonia - Boogie Woogie Flu", "rank": 9, "weeks": 19, "change": "-3"}, {"spotifyLink": "https://embed.spotify.com/?uri=spotify:track:2aqb3er36PfC0orJvMUBZU", "peakPos": 7, "artist": "War", "lastPos": 15, "title": "The World Is A Ghetto", "rank": 10, "weeks": 16, "change": "+5"}, {"spotifyLink": "none", "peakPos": 10, "artist": "Wings", "lastPos": 12, "title": "Hi, Hi, Hi", "rank": 11, "weeks": 11, "change": "+1"}, {"spotifyLink": "https://embed.spotify.com/?uri=spotify:track:2CqB4zujTn7BpO6mC3DLET", "peakPos": 8, "artist": "Curtis Mayfield", "lastPos": 8, "title": "Superfly", "rank": 12, "weeks": 15, "change": "-4"}, {"spotifyLink": "https://embed.spotify.com/?uri=spotify:track:3QrwftqtZ1D3jybjudsxnt", "peakPos": 6, "artist": "Steely Dan", "lastPos": 18, "title": "Do It Again", "rank": 13, "weeks": 17, "change": "+5"}, {"spotifyLink": "https://embed.spotify.com/?uri=spotify:track:6wAxiqfZzbxPUuvVan1ZuU", "peakPos": 2, "artist": "Gilbert O'Sullivan", "lastPos": 7, "title": "Clair", "rank": 14, "weeks": 16, "change": "-7"}, {"spotifyLink": "https://embed.spotify.com/?uri=spotify:track:3c3b5daSKE7C83YLIOrSnX", "peakPos": 14, "artist": "James Taylor", "lastPos": 14, "title": "Don't Let Me Be Lonely Tonight", "rank": 15, "weeks": 11, "change": "-1"}, {"spotifyLink": "https://embed.spotify.com/?uri=spotify:track:34iw6sqitgw6I899erGzHm", "peakPos": 16, "artist": "Raspberries", "lastPos": 17, "title": "I Wanna Be With You", "rank": 16, "weeks": 11, "change": "+1"}, {"spotifyLink": "https://embed.spotify.com/?uri=spotify:track:7ufDF5ePKsnxYgP0DAZoZE", "peakPos": 13, "artist": "King Harvest", "lastPos": 22, "title": "Dancing In The Moonlight", "rank": 17, "weeks": 22, "change": "+5"}, {"spotifyLink": "https://embed.spotify.com/?uri=spotify:track:46Qk7yYzkQq0b4wctCKP2M", "peakPos": 16, "artist": "Brighter Side Of Darkness", "lastPos": 19, "title": "Love Jones", "rank": 18, "weeks": 13, "change": "+1"}, {"spotifyLink": "https://embed.spotify.com/?uri=spotify:track:25X2aVZDUjPPxRWCmeYej5", "peakPos": 5, "artist": "Donna Fargo", "lastPos": 11, "title": "Funny Face", "rank": 19, "weeks": 20, "change": "-8"}, {"spotifyLink": "https://embed.spotify.com/?uri=spotify:track:2TtUTMm65xZeqmF721Txfk", "peakPos": 8, "artist": "Lobo", "lastPos": 26, "title": "Don't Expect Me To Be Your Friend", "rank": 20, "weeks": 13, "change": "+6"}, {"spotifyLink": "https://embed.spotify.com/?uri=spotify:track:2gme2e3R1SocAZVbxwWKpB", "peakPos": 20, "artist": "Elvis Presley", "lastPos": 23, "title": "Separate Ways", "rank": 21, "weeks": 12, "change": "+2"}, {"spotifyLink": "https://embed.spotify.com/?uri=spotify:track:0DjMhBt7aGjrbboFQeGYeG", "peakPos": 9, "artist": "John Denver", "lastPos": 25, "title": "Rocky Mountain High", "rank": 22, "weeks": 19, "change": "+3"}, {"spotifyLink": "https://embed.spotify.com/?uri=spotify:track:5i0urffBRKl09GSX2Jhdeh", "peakPos": 4, "artist": "The Spinners", "lastPos": 31, "title": "Could It Be I'm Falling In Love", "rank": 23, "weeks": 15, "change": "+8"}, {"spotifyLink": "https://embed.spotify.com/?uri=spotify:track:3VpMHLn9w0jWjvAsgpYvyz", "peakPos": 19, "artist": "Three Dog Night", "lastPos": 21, "title": "Pieces Of April", "rank": 24, "weeks": 14, "change": "-3"}, {"spotifyLink": "https://embed.spotify.com/?uri=spotify:track:2tux0ui8n2qdHdGpBnkhol", "peakPos": 9, "artist": "Jermaine Jackson", "lastPos": 28, "title": "Daddy's Home", "rank": 25, "weeks": 18, "change": "+3"}, {"spotifyLink": "none", "peakPos": 16, "artist": "The Blue Ridge Rangers", "lastPos": 29, "title": "Jambalaya (On The Bayou)", "rank": 26, "weeks": 16, "change": "+3"}, {"spotifyLink": "https://embed.spotify.com/?uri=spotify:track:7gYkNHaayMG36w8pIeqgPu", "peakPos": 25, "artist": "Joni Mitchell", "lastPos": 30, "title": "You Turn Me On, I'm A Radio", "rank": 27, "weeks": 16, "change": "+3"}, {"spotifyLink": "https://embed.spotify.com/?uri=spotify:track:37MaVsbA1LgzCN4x7QDcCN", "peakPos": 11, "artist": "Jethro Tull", "lastPos": 20, "title": "Living In The Past", "rank": 28, "weeks": 14, "change": "-8"}, {"spotifyLink": "https://embed.spotify.com/?uri=spotify:track:43xmFw2FhPnC7lvz1nSXwJ", "peakPos": 27, "artist": "Blue Haze", "lastPos": 27, "title": "Smoke Gets In Your Eyes", "rank": 29, "weeks": 14, "change": "-2"}, {"spotifyLink": "https://embed.spotify.com/?uri=spotify:track:205L0cxylGWHIZBKo8owys", "peakPos": 21, "artist": "Don McLean", "lastPos": 34, "title": "Dreidel", "rank": 30, "weeks": 12, "change": "+4"}, {"spotifyLink": "https://embed.spotify.com/?uri=spotify:track:7JxxxT1MFJ2ga4DlOElZY4", "peakPos": 10, "artist": "Four Tops", "lastPos": 16, "title": "Keeper Of The Castle", "rank": 31, "weeks": 12, "change": "-15"}, {"spotifyLink": "https://embed.spotify.com/?uri=spotify:track:7o3vUVAbaN1oPmjtQ7cquv", "peakPos": 17, "artist": "Bette Midler", "lastPos": 36, "title": "Do You Want To Dance?", "rank": 32, "weeks": 16, "change": "+4"}, {"spotifyLink": "https://embed.spotify.com/?uri=spotify:track:2smJHcKJ61IPYWcpzFucjc", "peakPos": 27, "artist": "Chuck Berry", "lastPos": 35, "title": "Reelin' & Rockin'", "rank": 33, "weeks": 13, "change": "+2"}, {"spotifyLink": "https://embed.spotify.com/?uri=spotify:track:3MIm1YYgQJYmrrZ9SSMtSh", "peakPos": 3, "artist": "Edward Bear", "lastPos": 43, "title": "Last Song", "rank": 34, "weeks": 18, "change": "+9"}, {"spotifyLink": "none", "peakPos": 31, "artist": "Bobby Womack & Peace", "lastPos": 37, "title": "Harry Hippie", "rank": 35, "weeks": 12, "change": "+2"}, {"spotifyLink": "https://embed.spotify.com/?uri=spotify:track:6tunhVGD8C05MZNjSVIsjw", "peakPos": 5, "artist": "Albert Hammond", "lastPos": 24, "title": "It Never Rains In Southern California", "rank": 36, "weeks": 16, "change": "-12"}, {"spotifyLink": "https://embed.spotify.com/?uri=spotify:track:7IWRBwbiWJ14YZcDHHmjf8", "peakPos": 1, "artist": "The O'Jays", "lastPos": 61, "title": "Love Train", "rank": 37, "weeks": 14, "change": "+24"}, {"spotifyLink": "https://embed.spotify.com/?uri=spotify:track:4bDIQEr0MPOHa2uMIqHkAc", "peakPos": 16, "artist": "Cat Stevens", "lastPos": 32, "title": "Sitting", "rank": 38, "weeks": 11, "change": "-6"}, {"spotifyLink": "none", "peakPos": 39, "artist": "The Partridge Family Starring Shirley Jones Featuring David Cassidy", "lastPos": 42, "title": "Looking Through The Eyes Of Love", "rank": 39, "weeks": 8, "change": "+3"}, {"spotifyLink": "https://embed.spotify.com/?uri=spotify:track:4CAey4iFN0nyncxkUwcdbl", "peakPos": 40, "artist": "Luther Ingram", "lastPos": 40, "title": "I'll Be Your Shelter (In Time Of Storm)", "rank": 40, "weeks": 11, "change": "0"}, {"spotifyLink": "none", "peakPos": 2, "artist": "Deliverance/Eric Weissberg & Steve Mandell", "lastPos": 64, "title": "Dueling Banjos", "rank": 41, "weeks": 14, "change": "+23"}, {"spotifyLink": "https://embed.spotify.com/?uri=spotify:track:0d62GFZpi2wIABXCi2C21M", "peakPos": 37, "artist": "Cornelius Brothers & Sister Rose", "lastPos": 44, "title": "I'm Never Gonna Be Alone Anymore", "rank": 42, "weeks": 9, "change": "+2"}, {"spotifyLink": "none", "peakPos": 6, "artist": "Dr. Hook And The Medicine Show", "lastPos": 49, "title": "The Cover Of Rolling Stone", "rank": 43, "weeks": 20, "change": "+6"}, {"spotifyLink": "https://embed.spotify.com/?uri=spotify:track:4jHJ878nu66JYt7Fnq8nUG", "peakPos": 22, "artist": "Eagles", "lastPos": 51, "title": "Peaceful Easy Feeling", "rank": 44, "weeks": 12, "change": "+7"}, {"spotifyLink": "https://embed.spotify.com/?uri=spotify:track:5Ae96OHQw8miHN8t814xUB", "peakPos": 45, "artist": "Smokey Robinson & The Miracles", "lastPos": 48, "title": "I Can't Stand To See You Cry", "rank": 45, "weeks": 8, "change": "+3"}, {"spotifyLink": "https://embed.spotify.com/?uri=spotify:track:2KTEXChscbbjtRoOTzzmDN", "peakPos": 39, "artist": "The Who", "lastPos": 39, "title": "The Relay", "rank": 46, "weeks": 8, "change": "-7"}, {"spotifyLink": "none", "peakPos": 32, "artist": "The 5th Dimension", "lastPos": 58, "title": "Living Together, Growing Together", "rank": 47, "weeks": 9, "change": "+11"}, {"spotifyLink": "https://embed.spotify.com/?uri=spotify:track:6UwnvWfqxjGv696ukUD7zF", "peakPos": 3, "artist": "Al Green", "lastPos": 38, "title": "You Ought To Be With Me", "rank": 48, "weeks": 15, "change": "-10"}, {"spotifyLink": "https://embed.spotify.com/?uri=spotify:track:6EfIwLAXkUuNXllq1r1YqG", "peakPos": 24, "artist": "Carole King", "lastPos": 33, "title": "Been To Canaan", "rank": 49, "weeks": 10, "change": "-16"}, {"spotifyLink": "https://embed.spotify.com/?uri=spotify:track:0SsvIpXMHfBeDY6Y2LfrAw", "peakPos": 23, "artist": "Gallery", "lastPos": 59, "title": "Big City Miss Ruth Ann", "rank": 50, "weeks": 15, "change": "+9"}, {"spotifyLink": "none", "peakPos": 27, "artist": "James Brown", "lastPos": 79, "title": "I Got Ants In My Pants (and i want to dance) (Part 1)", "rank": 51, "weeks": 8, "change": "+28"}, {"spotifyLink": "https://embed.spotify.com/?uri=spotify:track:23gNZrMffSn2P1C2JOUoD6", "peakPos": 46, "artist": "The Main Ingredient", "lastPos": 54, "title": "You've Got To Take It (If You Want It)", "rank": 52, "weeks": 9, "change": "+2"}, {"spotifyLink": "https://embed.spotify.com/?uri=spotify:track:3voA7jcES21idqh8dflNim", "peakPos": 35, "artist": "The Doobie Brothers", "lastPos": 56, "title": "Jesus Is Just Alright", "rank": 53, "weeks": 11, "change": "+3"}, {"spotifyLink": "https://embed.spotify.com/?uri=spotify:track:60SJRvzXJnVeVfS4RiH14u", "peakPos": 1, "artist": "Roberta Flack", "lastPos": 0, "title": "Killing Me Softly With His Song", "rank": 54, "weeks": 16, "change": "Re-Entry"}, {"spotifyLink": "https://embed.spotify.com/?uri=spotify:track:5nUM1Mvt7Kih7r02Nj7i6j", "peakPos": 48, "artist": "Emerson, Lake & Palmer", "lastPos": 57, "title": "Lucky Man", "rank": 55, "weeks": 19, "change": "+2"}, {"spotifyLink": "https://embed.spotify.com/?uri=spotify:track:23JXHMCEdQCgZmOrrPQBvP", "peakPos": 53, "artist": "Nilsson", "lastPos": 53, "title": "Remember (Christmas)", "rank": 56, "weeks": 6, "change": "-3"}, {"spotifyLink": "https://embed.spotify.com/?uri=spotify:track:5B7XVloJAOcTFinyvF5y2J", "peakPos": 52, "artist": "Holland-Dozier", "lastPos": 67, "title": "Don't Leave Me Starvin' For Your Love (Part 1)", "rank": 57, "weeks": 6, "change": "+10"}, {"spotifyLink": "https://embed.spotify.com/?uri=spotify:track:0fiJIRJN4qYSsaClPAAEMm", "peakPos": 56, "artist": "James Brown-Lyn Collins", "lastPos": 62, "title": "What My Baby Needs Now Is A Little More Lovin'", "rank": 58, "weeks": 7, "change": "+4"}, {"spotifyLink": "none", "peakPos": 51, "artist": "Keith Hampshire", "lastPos": 66, "title": "Daytime Night-Time", "rank": 59, "weeks": 9, "change": "+7"}, {"spotifyLink": "https://embed.spotify.com/?uri=spotify:track:5lQxMlCMTzCj3j4vyzdl8T", "peakPos": 7, "artist": "Anne Murray", "lastPos": 68, "title": "Danny's Song", "rank": 60, "weeks": 18, "change": "+8"}, {"spotifyLink": "https://embed.spotify.com/?uri=spotify:track:3MSOgxINnzigwwZ9bBcm1E", "peakPos": 34, "artist": "Diana Ross", "lastPos": 71, "title": "Good Morning Heartache", "rank": 61, "weeks": 13, "change": "+10"}, {"spotifyLink": "https://embed.spotify.com/?uri=spotify:track:1QpCfyttanc3ZSmLSw3dMb", "peakPos": 1, "artist": "The Temptations", "lastPos": 45, "title": "Papa Was A Rollin' Stone", "rank": 62, "weeks": 16, "change": "-17"}, {"spotifyLink": "https://embed.spotify.com/?uri=spotify:track:0X5NtrCEqriFUemE5TQ9zC", "peakPos": 20, "artist": "Seals & Crofts", "lastPos": 76, "title": "Hummingbird", "rank": 63, "weeks": 13, "change": "+13"}, {"spotifyLink": "https://embed.spotify.com/?uri=spotify:track:3rNgQNJ8dFcTxabYUnFwXd", "peakPos": 31, "artist": "Barbara Mason", "lastPos": 75, "title": "Give Me Your Love", "rank": 64, "weeks": 12, "change": "+11"}, {"spotifyLink": "https://embed.spotify.com/?uri=spotify:track:2AKedwFpYgXJWY7jmsHSja", "peakPos": 59, "artist": "Cashman & West", "lastPos": 69, "title": "Songman", "rank": 65, "weeks": 7, "change": "+4"}, {"spotifyLink": "https://embed.spotify.com/?uri=spotify:track:3nOSsEiT8qLPJP5HzNw1ps", "peakPos": 37, "artist": "Joe Stampley", "lastPos": 73, "title": "Soul Song", "rank": 66, "weeks": 13, "change": "+7"}, {"spotifyLink": "none", "peakPos": 61, "artist": "Engelbert Humperdinck", "lastPos": 70, "title": "I Never Said Goodbye", "rank": 67, "weeks": 7, "change": "+3"}, {"spotifyLink": "https://embed.spotify.com/?uri=spotify:track:6tLf3mkwdIt0Pb608vNQg4", "peakPos": 63, "artist": "Valerie Simpson", "lastPos": 74, "title": "Silly Wasn't I", "rank": 68, "weeks": 9, "change": "+6"}, {"spotifyLink": "none", "peakPos": 59, "artist": "Little Jimmy Osmond", "lastPos": 96, "title": "Tweedlee Dee", "rank": 69, "weeks": 6, "change": "+27"}, {"spotifyLink": "none", "peakPos": 56, "artist": "Joe Cocker and The Chris Stainton Band", "lastPos": 65, "title": "Woman To Woman", "rank": 70, "weeks": 9, "change": "-5"}, {"spotifyLink": "https://embed.spotify.com/?uri=spotify:track:3sb66av9ZpdI1JmPDHVa18", "peakPos": 15, "artist": "David Bowie", "lastPos": 0, "title": "Space Oddity", "rank": 71, "weeks": 14, "change": "Re-Entry"}, {"spotifyLink": "none", "peakPos": 72, "artist": "Merry Clayton", "lastPos": 77, "title": "Oh No, Not My Baby", "rank": 72, "weeks": 6, "change": "+5"}, {"spotifyLink": "https://embed.spotify.com/?uri=spotify:track:4la6sNSXSvlntijQafjt3G", "peakPos": 17, "artist": "Neil Diamond", "lastPos": 41, "title": "Walk On Water", "rank": 73, "weeks": 12, "change": "-32"}, {"spotifyLink": "none", "peakPos": 68, "artist": "Paul Davis", "lastPos": 80, "title": "Boogie Woogie Man", "rank": 74, "weeks": 9, "change": "+6"}, {"spotifyLink": "none", "peakPos": 51, "artist": "Les Emmerson", "lastPos": 86, "title": "Control Of Me", "rank": 75, "weeks": 9, "change": "+11"}, {"spotifyLink": "https://embed.spotify.com/?uri=spotify:track:2fqDuYbP9LsoiC1DiXDhWk", "peakPos": 35, "artist": "America", "lastPos": 0, "title": "Don't Cross The River", "rank": 76, "weeks": 8, "change": "Re-Entry"}, {"spotifyLink": "none", "peakPos": 76, "artist": "Rita Coolidge", "lastPos": 84, "title": "Fever/My Crew", "rank": 77, "weeks": 7, "change": "+7"}, {"spotifyLink": "https://embed.spotify.com/?uri=spotify:track:7a1Fb5S5fAgxYQTZkNLSid", "peakPos": 48, "artist": "Cymande", "lastPos": 85, "title": "The Message", "rank": 78, "weeks": 10, "change": "+7"}, {"spotifyLink": "none", "peakPos": 43, "artist": "Sam Neely", "lastPos": 0, "title": "Rosalie", "rank": 79, "weeks": 8, "change": "Re-Entry"}, {"spotifyLink": "https://embed.spotify.com/?uri=spotify:track:6D7Ga5YBxNuXpGAtkcV67Y", "peakPos": 67, "artist": "Bobby Darin", "lastPos": 83, "title": "Happy", "rank": 80, "weeks": 8, "change": "+3"}, {"spotifyLink": "https://embed.spotify.com/?uri=spotify:track:6I56ppsvv3V32jvOpH9Znb", "peakPos": 71, "artist": "Al Green", "lastPos": 93, "title": "Hot Wire", "rank": 81, "weeks": 5, "change": "+12"}, {"spotifyLink": "https://embed.spotify.com/?uri=spotify:track:3ctEdj1zbAJ7Jf9IjVERpB", "peakPos": 82, "artist": "Barbra Streisand", "lastPos": 82, "title": "Didn't We", "rank": 82, "weeks": 8, "change": "0"}, {"spotifyLink": "https://embed.spotify.com/?uri=spotify:track:0ZSJhbhBw7kXYW1XCT90r9", "peakPos": 46, "artist": "Bettye Swann", "lastPos": 0, "title": "Today I Started Loving You Again", "rank": 83, "weeks": 7, "change": "Re-Entry"}, {"spotifyLink": "none", "peakPos": 82, "artist": "Bobby Vinton", "lastPos": 88, "title": "But I Do", "rank": 84, "weeks": 6, "change": "+4"}, {"spotifyLink": "https://embed.spotify.com/?uri=spotify:track:6EdVvkxAYAgT3DXW8Op4ZH", "peakPos": 78, "artist": "Johnny Williams", "lastPos": 90, "title": "Slow Motion (Part 1)", "rank": 85, "weeks": 7, "change": "+5"}, {"spotifyLink": "https://embed.spotify.com/?uri=spotify:track:76Gcy0ltMutGaK8oizgdrF", "peakPos": 2, "artist": "Gladys Knight And The Pips", "lastPos": 0, "title": "Neither One Of Us (Wants To Be The First To Say Goodbye)", "rank": 86, "weeks": 16, "change": "Re-Entry"}, {"spotifyLink": "none", "peakPos": 68, "artist": "Travis Wammack", "lastPos": 91, "title": "How Can I Tell You", "rank": 87, "weeks": 7, "change": "+4"}, {"spotifyLink": "https://embed.spotify.com/?uri=spotify:track:3NWpG50DNlO8IiVdx6Ig3w", "peakPos": 16, "artist": "Loudon Wainwright III", "lastPos": 0, "title": "Dead Skunk", "rank": 88, "weeks": 13, "change": "Re-Entry"}, {"spotifyLink": "https://embed.spotify.com/?uri=spotify:track:4AMClVJoeDFESypfYmreZj", "peakPos": 89, "artist": "Shawn Phillips", "lastPos": 92, "title": "We", "rank": 89, "weeks": 3, "change": "+3"}, {"spotifyLink": "none", "peakPos": 90, "artist": "Anacostia", "lastPos": 95, "title": "On And Off (Part 1)", "rank": 90, "weeks": 4, "change": "+5"}, {"spotifyLink": "none", "peakPos": 55, "artist": "The Grass Roots", "lastPos": 0, "title": "Love Is What You Make It", "rank": 91, "weeks": 10, "change": "Re-Entry"}, {"spotifyLink": "https://embed.spotify.com/?uri=spotify:track:75SqDz1tR1tiJKt01N79c2", "peakPos": 3, "artist": "The Sweet", "lastPos": 99, "title": "Little Willy", "rank": 92, "weeks": 23, "change": "+7"}, {"spotifyLink": "none", "peakPos": 91, "artist": "Uriah Heep", "lastPos": 97, "title": "Blind Eye/Sweet Lorraine", "rank": 93, "weeks": 3, "change": "+4"}, {"spotifyLink": "none", "peakPos": 79, "artist": "Paul Kelly", "lastPos": 0, "title": "Don't Burn Me", "rank": 94, "weeks": 5, "change": "Re-Entry"}, {"spotifyLink": "https://embed.spotify.com/?uri=spotify:track:5BlpARRLo6vhyK9QjT8akG", "peakPos": 95, "artist": "Millie Jackson", "lastPos": 100, "title": "I Miss You Baby", "rank": 95, "weeks": 4, "change": "+5"}, {"spotifyLink": "https://embed.spotify.com/?uri=spotify:track:3xyJQopi3TWy2ouP5A3EcS", "peakPos": 96, "artist": "Mott The Hoople", "lastPos": 0, "title": "One Of The Boys", "rank": 96, "weeks": 1, "change": "Hot Shot Debut"}, {"spotifyLink": "none", "peakPos": 97, "artist": "Dottie West", "lastPos": 98, "title": "If It's All Right With You", "rank": 97, "weeks": 3, "change": "+1"}, {"spotifyLink": "none", "peakPos": 94, "artist": "The Whispers", "lastPos": 0, "title": "Somebody Loves You", "rank": 98, "weeks": 4, "change": "Re-Entry"}, {"spotifyLink": "https://embed.spotify.com/?uri=spotify:track:17lB2JxpYDMrJiDHJ1ewY8", "peakPos": 93, "artist": "Rare Earth", "lastPos": 0, "title": "We're Gonna Have A Good Time", "rank": 99, "weeks": 3, "change": "Re-Entry"}, {"spotifyLink": "https://embed.spotify.com/?uri=spotify:track:5xfcdKghQ2xfhqbCcvRiW3", "peakPos": 95, "artist": "The New Seekers", "lastPos": 0, "title": "Come Softly To Me", "rank": 100, "weeks": 3, "change": "Re-Entry"}], "latest": false, "name": "hot-100", "previousDate": "1973-01-20"}