{"date": "1976-09-04", "entries": [{"spotifyLink": "https://embed.spotify.com/?uri=spotify:track:5VAKsbOWGdBbg1VFlu9W8o", "peakPos": 1, "artist": "Bee Gees", "lastPos": 2, "title": "You Should Be Dancing", "rank": 1, "weeks": 20, "change": "+1"}, {"spotifyLink": "https://embed.spotify.com/?uri=spotify:track:4bEtg70srLrCqQp3Nm2T5R", "peakPos": 2, "artist": "Lou Rawls", "lastPos": 4, "title": "You'll Never Find Another Love Like Mine", "rank": 2, "weeks": 21, "change": "+2"}, {"spotifyLink": "https://embed.spotify.com/?uri=spotify:track:2xAacCD0MW3UBFugKVHbJc", "peakPos": 3, "artist": "Wings", "lastPos": 3, "title": "Let 'em In", "rank": 3, "weeks": 16, "change": "0"}, {"spotifyLink": "https://embed.spotify.com/?uri=spotify:track:51WE0PFRB0hCSp9mDC5p8u", "peakPos": 2, "artist": "England Dan & John Ford Coley", "lastPos": 5, "title": "I'd Really Love To See You Tonight", "rank": 4, "weeks": 24, "change": "+1"}, {"spotifyLink": "https://embed.spotify.com/?uri=spotify:track:5av2sOP0wLIg3rZOhwUMHV", "peakPos": 1, "artist": "KC And The Sunshine Band", "lastPos": 6, "title": "(Shake, Shake, Shake) Shake Your Booty", "rank": 5, "weeks": 21, "change": "+1"}, {"spotifyLink": "https://embed.spotify.com/?uri=spotify:track:0D7L4pBEGv8ni1cRfaTdMJ", "peakPos": 1, "artist": "Wild Cherry", "lastPos": 7, "title": "Play That Funky Music", "rank": 6, "weeks": 25, "change": "+1"}, {"spotifyLink": "none", "peakPos": 1, "artist": "Walter Murphy & The Big Apple Band", "lastPos": 8, "title": "A Fifth Of Beethoven", "rank": 7, "weeks": 28, "change": "+1"}, {"spotifyLink": "https://embed.spotify.com/?uri=spotify:track:7cKUyLDvGKMd12ovtOU0z5", "peakPos": 1, "artist": "Elton John & Kiki Dee", "lastPos": 1, "title": "Don't Go Breaking My Heart", "rank": 8, "weeks": 20, "change": "-7"}, {"spotifyLink": "https://embed.spotify.com/?uri=spotify:track:20MxJN12WEqU5eWsuCrwM5", "peakPos": 3, "artist": "Boz Scaggs", "lastPos": 16, "title": "Lowdown", "rank": 9, "weeks": 22, "change": "+7"}, {"spotifyLink": "https://embed.spotify.com/?uri=spotify:track:2skIFujR9zTTAEXj8tfrw0", "peakPos": 10, "artist": "George Benson", "lastPos": 10, "title": "This Masquerade", "rank": 10, "weeks": 19, "change": "0"}, {"spotifyLink": "https://embed.spotify.com/?uri=spotify:track:0UHMAa700hzpQVmHlDGE7e", "peakPos": 7, "artist": "War", "lastPos": 13, "title": "Summer", "rank": 11, "weeks": 16, "change": "+2"}, {"spotifyLink": "https://embed.spotify.com/?uri=spotify:track:1ksayCHVLH4eKFm43GFokU", "peakPos": 12, "artist": "Peter Frampton", "lastPos": 12, "title": "Baby, I Love Your Way", "rank": 12, "weeks": 16, "change": "0"}, {"spotifyLink": "none", "peakPos": 11, "artist": "Fleetwood Mac", "lastPos": 14, "title": "Say You Love Me", "rank": 13, "weeks": 19, "change": "+1"}, {"spotifyLink": "none", "peakPos": 6, "artist": "Seals & Crofts (Featuring Carolyn Willis)", "lastPos": 9, "title": "Get Closer", "rank": 14, "weeks": 26, "change": "-5"}, {"spotifyLink": "https://embed.spotify.com/?uri=spotify:track:00lbSgTwyh8Es8RcSnijDv", "peakPos": 15, "artist": "Tavares", "lastPos": 17, "title": "Heaven Must Be Missing An Angel (part 1)", "rank": 15, "weeks": 21, "change": "+2"}, {"spotifyLink": "https://embed.spotify.com/?uri=spotify:track:3oyNzDC9uT8u0yjfBBZa2y", "peakPos": 12, "artist": "Jefferson Starship", "lastPos": 19, "title": "With Your Love", "rank": 16, "weeks": 17, "change": "+3"}, {"spotifyLink": "https://embed.spotify.com/?uri=spotify:track:7tV4IBfyJN1E9rC9lxkl2Z", "peakPos": 6, "artist": "Cliff Richard", "lastPos": 20, "title": "Devil Woman", "rank": 17, "weeks": 22, "change": "+3"}, {"spotifyLink": "https://embed.spotify.com/?uri=spotify:track:0KMGxYKeUzK9wc5DZCt3HT", "peakPos": 1, "artist": "Chicago", "lastPos": 24, "title": "If You Leave Me Now", "rank": 18, "weeks": 21, "change": "+6"}, {"spotifyLink": "https://embed.spotify.com/?uri=spotify:track:3qZuggj5VKuhntEdXsz1SK", "peakPos": 11, "artist": "Dr. Hook", "lastPos": 21, "title": "A Little Bit More", "rank": 19, "weeks": 24, "change": "+2"}, {"spotifyLink": "https://embed.spotify.com/?uri=spotify:track:32UDt5O32Ju7gTQWI3Pb7c", "peakPos": 5, "artist": "Orleans", "lastPos": 22, "title": "Still The One", "rank": 20, "weeks": 18, "change": "+2"}, {"spotifyLink": "https://embed.spotify.com/?uri=spotify:track:0XaKKWRNWX2TDQ8KgqvVfK", "peakPos": 18, "artist": "Ohio Players", "lastPos": 23, "title": "Who'd She Coo?", "rank": 21, "weeks": 17, "change": "+2"}, {"spotifyLink": "https://embed.spotify.com/?uri=spotify:track:5vVuiXoHyRGxJeCaHUpgae", "peakPos": 2, "artist": "Gary Wright", "lastPos": 15, "title": "Love Is Alive", "rank": 22, "weeks": 27, "change": "-7"}, {"spotifyLink": "none", "peakPos": 16, "artist": "Silver", "lastPos": 25, "title": "Wham Bam (Shang-A-Lang)", "rank": 23, "weeks": 21, "change": "+2"}, {"spotifyLink": "https://embed.spotify.com/?uri=spotify:track:6roaUdrIQUlTcujSFLtYKI", "peakPos": 1, "artist": "The Manhattans", "lastPos": 11, "title": "Kiss And Say Goodbye", "rank": 24, "weeks": 26, "change": "-13"}, {"spotifyLink": "https://embed.spotify.com/?uri=spotify:track:08TT1DfijaOu762vH4bZBM", "peakPos": 7, "artist": "Daryl Hall  John Oates", "lastPos": 27, "title": "She's Gone", "rank": 25, "weeks": 28, "change": "+2"}, {"spotifyLink": "https://embed.spotify.com/?uri=spotify:track:0RJ6CvfsnjMK3v4KK4Y6fo", "peakPos": 22, "artist": "James Taylor", "lastPos": 28, "title": "Shower The People", "rank": 26, "weeks": 16, "change": "+2"}, {"spotifyLink": "https://embed.spotify.com/?uri=spotify:track:6HRopt34n9yeJGrYzhxwMg", "peakPos": 12, "artist": "Earth, Wind & Fire", "lastPos": 29, "title": "Getaway", "rank": 27, "weeks": 19, "change": "+2"}, {"spotifyLink": "https://embed.spotify.com/?uri=spotify:track:0qbVccbQLEMbfJcI5wNLTJ", "peakPos": 5, "artist": "The Beach Boys", "lastPos": 18, "title": "Rock And Roll Music", "rank": 28, "weeks": 17, "change": "-10"}, {"spotifyLink": "none", "peakPos": 27, "artist": "Lady Flash", "lastPos": 31, "title": "Street Singin'", "rank": 29, "weeks": 12, "change": "+2"}, {"spotifyLink": "none", "peakPos": 29, "artist": "Helen Reddy", "lastPos": 33, "title": "I Can't Hear You No More/Music Is My Life", "rank": 30, "weeks": 9, "change": "+3"}, {"spotifyLink": "https://embed.spotify.com/?uri=spotify:track:2TziLOnBMT8kDVo2LA1X6t", "peakPos": 10, "artist": "Vicki Sue Robinson", "lastPos": 26, "title": "Turn The Beat Around", "rank": 31, "weeks": 25, "change": "-5"}, {"spotifyLink": "https://embed.spotify.com/?uri=spotify:track:1Q0upLHepnwMjcb7kUpoiv", "peakPos": 25, "artist": "Diana Ross", "lastPos": 36, "title": "One Love In My Lifetime", "rank": 32, "weeks": 12, "change": "+4"}, {"spotifyLink": "https://embed.spotify.com/?uri=spotify:track:3MFa9idQuY4iJLWsZl3tIQ", "peakPos": 20, "artist": "Candi Staton", "lastPos": 35, "title": "Young Hearts Run Free", "rank": 33, "weeks": 16, "change": "+2"}, {"spotifyLink": "none", "peakPos": 1, "artist": "Rick Dees & His Cast Of Idiots", "lastPos": 63, "title": "Disco Duck (Part I)", "rank": 34, "weeks": 25, "change": "+29"}, {"spotifyLink": "https://embed.spotify.com/?uri=spotify:track:4sUlsy0tPv9n5nqrqeA0lE", "peakPos": 9, "artist": "Heart", "lastPos": 41, "title": "Magic Man", "rank": 35, "weeks": 23, "change": "+6"}, {"spotifyLink": "https://embed.spotify.com/?uri=spotify:track:0GmRPoU0PrO1crMm7mB7zg", "peakPos": 1, "artist": "Starland Vocal Band", "lastPos": 30, "title": "Afternoon Delight", "rank": 36, "weeks": 20, "change": "-6"}, {"spotifyLink": "https://embed.spotify.com/?uri=spotify:track:2luzxyVgeKvene3XtzUcQk", "peakPos": 1, "artist": "Steve Miller", "lastPos": 56, "title": "Rock'n Me", "rank": 37, "weeks": 18, "change": "+19"}, {"spotifyLink": "https://embed.spotify.com/?uri=spotify:track:6wYONACNxveMgMpP3Jx63o", "peakPos": 11, "artist": "Linda Ronstadt", "lastPos": 57, "title": "That'll Be The Day", "rank": 38, "weeks": 16, "change": "+19"}, {"spotifyLink": "https://embed.spotify.com/?uri=spotify:track:4IFpOAdAF2Rh2ulMw91gpd", "peakPos": 33, "artist": "Olivia Newton-John", "lastPos": 47, "title": "Don't Stop Believin'", "rank": 39, "weeks": 9, "change": "+8"}, {"spotifyLink": "https://embed.spotify.com/?uri=spotify:track:2NL4BBBSgypHnxUKmQdYcT", "peakPos": 12, "artist": "Blue Oyster Cult", "lastPos": 49, "title": "(Don't Fear) The Reaper", "rank": 40, "weeks": 20, "change": "+9"}, {"spotifyLink": "https://embed.spotify.com/?uri=spotify:track:6dWGsVvo1zuppeu0pmlb79", "peakPos": 37, "artist": "The Alan Parsons Project", "lastPos": 43, "title": "(The System Of) Doctor Tarr And Professor Fether", "rank": 41, "weeks": 10, "change": "+2"}, {"spotifyLink": "https://embed.spotify.com/?uri=spotify:track:4UN5z3IkTamNxngTsS3Qrm", "peakPos": 17, "artist": "Keith Carradine", "lastPos": 32, "title": "I'm Easy", "rank": 42, "weeks": 19, "change": "-10"}, {"spotifyLink": "https://embed.spotify.com/?uri=spotify:track:1FMaDhxbLJanh9NpqPZIw0", "peakPos": 3, "artist": "Starbuck", "lastPos": 34, "title": "Moonlight Feels Right", "rank": 43, "weeks": 22, "change": "-9"}, {"spotifyLink": "none", "peakPos": 35, "artist": "Paul Davis", "lastPos": 52, "title": "Superstar", "rank": 44, "weeks": 9, "change": "+8"}, {"spotifyLink": "https://embed.spotify.com/?uri=spotify:track:0wtqqSTlOJJjred8ySfNDI", "peakPos": 37, "artist": "Henry Gross", "lastPos": 37, "title": "Springtime Mama", "rank": 45, "weeks": 10, "change": "-8"}, {"spotifyLink": "https://embed.spotify.com/?uri=spotify:track:4QWVQr6iA4jDSzj5thJN72", "peakPos": 43, "artist": "Michael Franks", "lastPos": 58, "title": "Popsicle Toes", "rank": 46, "weeks": 8, "change": "+12"}, {"spotifyLink": "https://embed.spotify.com/?uri=spotify:track:0nyrltZrQGAJMBZc1bYvuQ", "peakPos": 45, "artist": "James Brown", "lastPos": 55, "title": "Get Up Offa That Thing", "rank": 47, "weeks": 7, "change": "+8"}, {"spotifyLink": "none", "peakPos": 48, "artist": "Shirley & Squirrely", "lastPos": 50, "title": "Hey Shirley (This Is Squirrely)", "rank": 48, "weeks": 9, "change": "+2"}, {"spotifyLink": "https://embed.spotify.com/?uri=spotify:track:00PLtXXER1XcTRZvs3LioS", "peakPos": 30, "artist": "The Brothers Johnson", "lastPos": 61, "title": "Get The Funk Out Ma Face", "rank": 49, "weeks": 15, "change": "+12"}, {"spotifyLink": "https://embed.spotify.com/?uri=spotify:track:6HNNaAxU40FRQa9pPHhBgm", "peakPos": 11, "artist": "Neil Diamond", "lastPos": 48, "title": "If You Know What I Mean", "rank": 50, "weeks": 12, "change": "-2"}, {"spotifyLink": "https://embed.spotify.com/?uri=spotify:track:2Fns5n1hiCpoSO7iI8pyo1", "peakPos": 45, "artist": "Grand Funk Railroad", "lastPos": 62, "title": "Can You Do It", "rank": 51, "weeks": 7, "change": "+11"}, {"spotifyLink": "https://embed.spotify.com/?uri=spotify:track:0sL2gIDdJ5Qb4J9C7ggmln", "peakPos": 52, "artist": "Leon & Mary Russell", "lastPos": 54, "title": "Rainbow In Your Eyes", "rank": 52, "weeks": 12, "change": "+2"}, {"spotifyLink": "https://embed.spotify.com/?uri=spotify:track:0Lkf8mbEreomh1CcjEyLir", "peakPos": 7, "artist": "The Beatles", "lastPos": 38, "title": "Got To Get You Into My Life", "rank": 53, "weeks": 16, "change": "-15"}, {"spotifyLink": "https://embed.spotify.com/?uri=spotify:track:2C1sBb37TwsHFHDEEP45LI", "peakPos": 10, "artist": "John Travolta", "lastPos": 44, "title": "Let Her In", "rank": 54, "weeks": 20, "change": "-10"}, {"spotifyLink": "https://embed.spotify.com/?uri=spotify:track:4CCQ9mf2YcGxsgJH80iB8I", "peakPos": 34, "artist": "Eric Carmen", "lastPos": 66, "title": "Sunrise", "rank": 55, "weeks": 10, "change": "+11"}, {"spotifyLink": "none", "peakPos": 40, "artist": "Red Sovine", "lastPos": 40, "title": "Teddy Bear", "rank": 56, "weeks": 9, "change": "-16"}, {"spotifyLink": "https://embed.spotify.com/?uri=spotify:track:1FZYlrtXXPK9ajGPhrpQxO", "peakPos": 2, "artist": "Gordon Lightfoot", "lastPos": 70, "title": "The Wreck Of The Edmund Fitzgerald", "rank": 57, "weeks": 21, "change": "+13"}, {"spotifyLink": "https://embed.spotify.com/?uri=spotify:track:7gpavVMJwJYFNUzfzUdSv7", "peakPos": 21, "artist": "Aerosmith", "lastPos": 39, "title": "Last Child", "rank": 58, "weeks": 15, "change": "-19"}, {"spotifyLink": "https://embed.spotify.com/?uri=spotify:track:4vEXJ6NvEwS8ptynkNswaa", "peakPos": 16, "artist": "Queen", "lastPos": 42, "title": "You're My Best Friend", "rank": 59, "weeks": 16, "change": "-17"}, {"spotifyLink": "https://embed.spotify.com/?uri=spotify:track:2msoRIPYKdmewjWzSoEiJw", "peakPos": 60, "artist": "Silver Convention", "lastPos": 60, "title": "No, No, Joe", "rank": 60, "weeks": 6, "change": "0"}, {"spotifyLink": "https://embed.spotify.com/?uri=spotify:track:3H8fyH9qqRnAN7kvUhpOUP", "peakPos": 58, "artist": "Dorothy Moore", "lastPos": 65, "title": "Funny How Time Slips Away", "rank": 61, "weeks": 11, "change": "+4"}, {"spotifyLink": "https://embed.spotify.com/?uri=spotify:track:707Sfl5gopQ04y2WcqBIc0", "peakPos": 9, "artist": "Firefall", "lastPos": 72, "title": "You Are The Woman", "rank": 62, "weeks": 22, "change": "+10"}, {"spotifyLink": "https://embed.spotify.com/?uri=spotify:track:51OUHXIHL0v6dgF2zNaw8P", "peakPos": 41, "artist": "Rick Springfield", "lastPos": 73, "title": "Take A Hand", "rank": 63, "weeks": 9, "change": "+10"}, {"spotifyLink": "https://embed.spotify.com/?uri=spotify:track:6ChwVihLdousRshyZdF277", "peakPos": 29, "artist": "The Beach Boys", "lastPos": 77, "title": "It's O.k.", "rank": 64, "weeks": 10, "change": "+13"}, {"spotifyLink": "https://embed.spotify.com/?uri=spotify:track:78K0CsNamJ1LdSrWO7CxCn", "peakPos": 61, "artist": "Sherbet", "lastPos": 75, "title": "Howzat", "rank": 65, "weeks": 8, "change": "+10"}, {"spotifyLink": "https://embed.spotify.com/?uri=spotify:track:1kuFlMyndKP47bzilO2IGy", "peakPos": 25, "artist": "Natalie Cole", "lastPos": 45, "title": "Sophisticated Lady (She's A Different Lady)", "rank": 66, "weeks": 16, "change": "-21"}, {"spotifyLink": "https://embed.spotify.com/?uri=spotify:track:4rgVabEmcY7usX7lBzbG6J", "peakPos": 46, "artist": "John Handy", "lastPos": 46, "title": "Hard Work", "rank": 67, "weeks": 12, "change": "-21"}, {"spotifyLink": "https://embed.spotify.com/?uri=spotify:track:5lIQ4dFhncseTMYRl9Btes", "peakPos": 53, "artist": "Electric Light Orchestra", "lastPos": 59, "title": "Showdown", "rank": 68, "weeks": 18, "change": "-9"}, {"spotifyLink": "https://embed.spotify.com/?uri=spotify:track:03vFkuW9KnIkHxfpgGJmN9", "peakPos": 17, "artist": "The Ritchie Family", "lastPos": 81, "title": "The Best Disco In Town", "rank": 69, "weeks": 20, "change": "+12"}, {"spotifyLink": "none", "peakPos": 62, "artist": "Ronnie Dyson", "lastPos": 76, "title": "The More You Do It (The More I Like It Done To Me)", "rank": 70, "weeks": 12, "change": "+6"}, {"spotifyLink": "https://embed.spotify.com/?uri=spotify:track:2hhtp8ujKnHX7xqWvL0PLw", "peakPos": 69, "artist": "Van Mccoy", "lastPos": 71, "title": "Party", "rank": 71, "weeks": 5, "change": "0"}, {"spotifyLink": "https://embed.spotify.com/?uri=spotify:track:5tpcH9asFcRSn3xC6jqELq", "peakPos": 63, "artist": "The Isley Brothers", "lastPos": 82, "title": "Harvest For The World", "rank": 72, "weeks": 11, "change": "+10"}, {"spotifyLink": "https://embed.spotify.com/?uri=spotify:track:1mvriXWUwJh0RAzERwlRkj", "peakPos": 27, "artist": "Norman Connors", "lastPos": 83, "title": "You Are My Starship", "rank": 73, "weeks": 16, "change": "+10"}, {"spotifyLink": "https://embed.spotify.com/?uri=spotify:track:2gfwBhLhLkFkUlDfUOvM9d", "peakPos": 74, "artist": "Marvin Gaye", "lastPos": 74, "title": "After The Dance", "rank": 74, "weeks": 5, "change": "0"}, {"spotifyLink": "none", "peakPos": 29, "artist": "Flash Cadillac And The Continental Kids", "lastPos": 87, "title": "Did You Boogie (With Your Baby)", "rank": 75, "weeks": 14, "change": "+12"}, {"spotifyLink": "https://embed.spotify.com/?uri=spotify:track:55GVsKKsr8rgZImBoP1r7l", "peakPos": 75, "artist": "America", "lastPos": 79, "title": "Amber Cascades", "rank": 76, "weeks": 4, "change": "+3"}, {"spotifyLink": "https://embed.spotify.com/?uri=spotify:track:5Ovo27BHKAcGATt5hOzJ4T", "peakPos": 13, "artist": "ABBA", "lastPos": 0, "title": "Fernando", "rank": 77, "weeks": 16, "change": "Re-Entry"}, {"spotifyLink": "none", "peakPos": 8, "artist": "Barry DeVorzon and Perry Botkin, Jr.", "lastPos": 88, "title": "Nadia's Theme (The Young And The Restless)", "rank": 78, "weeks": 22, "change": "+10"}, {"spotifyLink": "none", "peakPos": 7, "artist": "Kiss", "lastPos": 0, "title": "Beth/Detroit Rock City", "rank": 79, "weeks": 21, "change": "Re-Entry"}, {"spotifyLink": "https://embed.spotify.com/?uri=spotify:track:3373VKGKgKdlBHccBgh645", "peakPos": 76, "artist": "Eddie Rabbitt", "lastPos": 84, "title": "Rocky Mountain Music", "rank": 80, "weeks": 8, "change": "+4"}, {"spotifyLink": "https://embed.spotify.com/?uri=spotify:track:5uTa94zby70qpi52o9NKVM", "peakPos": 66, "artist": "Jigsaw", "lastPos": 85, "title": "Brand New Love Affair", "rank": 81, "weeks": 7, "change": "+4"}, {"spotifyLink": "https://embed.spotify.com/?uri=spotify:track:2dyluelLGdgYWoJDwDuNXq", "peakPos": 40, "artist": "Average White Band", "lastPos": 0, "title": "Queen Of My Soul", "rank": 82, "weeks": 8, "change": "Re-Entry"}, {"spotifyLink": "https://embed.spotify.com/?uri=spotify:track:6dlEzWGKXrUPuIzdCjEu3c", "peakPos": 12, "artist": "Bay City Rollers", "lastPos": 0, "title": "I Only Want To Be With You", "rank": 83, "weeks": 16, "change": "Re-Entry"}, {"spotifyLink": "none", "peakPos": 78, "artist": "Barry Mann", "lastPos": 89, "title": "The Princess And The Punk", "rank": 84, "weeks": 6, "change": "+5"}, {"spotifyLink": "https://embed.spotify.com/?uri=spotify:track:08DoiXlJBCREfUR1zqVvCp", "peakPos": 85, "artist": "Atlanta Rhythm Section", "lastPos": 93, "title": "Free Spirit", "rank": 85, "weeks": 3, "change": "+8"}, {"spotifyLink": "https://embed.spotify.com/?uri=spotify:track:2MeVj7IlTZ3rCJMHdjZo2Z", "peakPos": 86, "artist": "Derringer", "lastPos": 86, "title": "Let Me In", "rank": 86, "weeks": 2, "change": "0"}, {"spotifyLink": "https://embed.spotify.com/?uri=spotify:track:5g7aKEM3a2S0TJazJ8cgX7", "peakPos": 87, "artist": "The Doobie Brothers", "lastPos": 92, "title": "Wheels Of Fortune", "rank": 87, "weeks": 2, "change": "+5"}, {"spotifyLink": "https://embed.spotify.com/?uri=spotify:track:4f9rMlaEXarzT44ju4T9bN", "peakPos": 67, "artist": "Gallagher And Lyle", "lastPos": 91, "title": "Heart On My Sleeve", "rank": 88, "weeks": 8, "change": "+3"}, {"spotifyLink": "https://embed.spotify.com/?uri=spotify:track:0akS5CnravKgyWljlRiJms", "peakPos": 56, "artist": "Carpenters", "lastPos": 0, "title": "Goofus", "rank": 89, "weeks": 5, "change": "Re-Entry"}, {"spotifyLink": "none", "peakPos": 66, "artist": "Diana Williams", "lastPos": 0, "title": "Teddy Bear's Last Ride", "rank": 90, "weeks": 6, "change": "Re-Entry"}, {"spotifyLink": "none", "peakPos": 37, "artist": "John Valenti", "lastPos": 0, "title": "Anything You Want", "rank": 91, "weeks": 12, "change": "Re-Entry"}, {"spotifyLink": "none", "peakPos": 88, "artist": "The Whispers", "lastPos": 98, "title": "One For The Money (part 1)", "rank": 92, "weeks": 10, "change": "+6"}, {"spotifyLink": "none", "peakPos": 92, "artist": "Ellison Chase", "lastPos": 97, "title": "Let's Rock", "rank": 93, "weeks": 3, "change": "+4"}, {"spotifyLink": "https://embed.spotify.com/?uri=spotify:track:19pM2X8hdrLb8YW0WegADR", "peakPos": 93, "artist": "Mother's Finest", "lastPos": 0, "title": "Fire", "rank": 94, "weeks": 2, "change": "Re-Entry"}, {"spotifyLink": "none", "peakPos": 95, "artist": "Spin", "lastPos": 95, "title": "Grasshopper", "rank": 95, "weeks": 2, "change": "0"}, {"spotifyLink": "none", "peakPos": 53, "artist": "Maxine Nightingale", "lastPos": 99, "title": "Gotta Be The One", "rank": 96, "weeks": 8, "change": "+3"}, {"spotifyLink": "none", "peakPos": 94, "artist": "Attitudes", "lastPos": 0, "title": "Sweet Summer Music", "rank": 97, "weeks": 6, "change": "Re-Entry"}, {"spotifyLink": "https://embed.spotify.com/?uri=spotify:track:43DeSV93pJPT4lCZaWZ6b1", "peakPos": 12, "artist": "Thin Lizzy", "lastPos": 53, "title": "The Boys Are Back In Town", "rank": 98, "weeks": 17, "change": "-45"}, {"spotifyLink": "https://embed.spotify.com/?uri=spotify:track:550WUwe2By7lQYiF5Tnp4U", "peakPos": 64, "artist": "The Real Thing", "lastPos": 64, "title": "You To Me Are Everything", "rank": 99, "weeks": 8, "change": "-35"}, {"spotifyLink": "none", "peakPos": 15, "artist": "Parliament", "lastPos": 51, "title": "Tear The Roof Off The Sucker (Give Up The Funk)", "rank": 100, "weeks": 17, "change": "-49"}], "latest": false, "name": "hot-100", "previousDate": "1976-08-28"}